ascend_deploy/__init__.py
ascend_deploy/address_config.py
ascend_deploy/ascend_deploy.py
ascend_deploy/ascend_download.py
ascend_deploy/helpers/__init__.py
ascend_deploy/helpers/config.py
ascend_deploy/helpers/deploy_functions.py
ascend_deploy/helpers/deployment_class.py
ascend_deploy-1.3.dist-info/LICENSE
ascend_deploy-1.3.dist-info/METADATA
ascend_deploy-1.3.dist-info/WHEEL
ascend_deploy-1.3.dist-info/entry_points.txt
ascend_deploy-1.3.dist-info/top_level.txt
ascend_deploy-1.3.dist-info/RECORD
