Metadata-Version: 2.1
Name: ascend-deploy
Version: 1.3
Summary: ascend_deploy
Home-page: UNKNOWN
Author: xisy
Author-email: thbeh@thbeh.com
License: UNKNOWN
Platform: UNKNOWN
Classifier: Programming Language :: Python :: 3
Classifier: License :: OSI Approved :: MIT License
Classifier: Operating System :: OS Independent
Requires-Python: >=3.7
Requires-Dist: ascend-io-sdk (==0.2.30)
Requires-Dist: pyyaml
